nginx_language_server/__init__.py
nginx_language_server/cli.py
nginx_language_server/data/directives.json
nginx_language_server/data/directives_document.json
nginx_language_server/data/snippets.json
nginx_language_server/data/variables.json
nginx_language_server/data/variables_document.json
nginx_language_server/parser/__init__.py
nginx_language_server/parser/data.py
nginx_language_server/parser/nginxconf.py
nginx_language_server/parser/utils.py
nginx_language_server/pygls_utils.py
nginx_language_server/server.py
nginx_language_server-0.9.0.dist-info/LICENSE
nginx_language_server-0.9.0.dist-info/METADATA
nginx_language_server-0.9.0.dist-info/WHEEL
nginx_language_server-0.9.0.dist-info/entry_points.txt
nginx_language_server-0.9.0.dist-info/RECORD
