Metadata-Version: 2.3
Name: nginx-language-server
Version: 0.9.0
Summary: A language server for nginx.conf
License: GPL-3.0-only
Keywords: nginx,completion,refactoring,vim,neovim,lsp,language-server-protocol
Author: Sam Roeca
Author-email: samuel.roeca@gmail.com
Requires-Python: >=3.9,<3.14
Classifier: Development Status :: 2 - Pre-Alpha
Classifier: Intended Audience :: Developers
Classifier: License :: OSI Approved :: GNU General Public License v3 (GPLv3)
Classifier: Operating System :: OS Independent
Classifier: Programming Language :: Python :: 3
Classifier: Programming Language :: Python :: 3.9
Classifier: Programming Language :: Python :: 3.10
Classifier: Programming Language :: Python :: 3.11
Classifier: Programming Language :: Python :: 3.12
Classifier: Programming Language :: Python :: 3.13
Classifier: Topic :: Software Development :: Code Generators
Classifier: Topic :: Software Development :: Libraries :: Python Modules
Classifier: Topic :: Text Editors :: Integrated Development Environments (IDE)
Classifier: Topic :: Utilities
Classifier: Typing :: Typed
Requires-Dist: crossplane (>=0.5.8,<0.6.0)
Requires-Dist: lsprotocol (>=2023.0.1)
Requires-Dist: pydantic (>=1.10.19,<2.0.0)
Requires-Dist: pygls (>=1.3.1,<2.0.0)
Requires-Dist: typing-extensions (>=4.12.2)
Project-URL: Changelog, https://github.com/pappasam/nginx-language-server/blob/main/CHANGELOG.md
Project-URL: Homepage, https://github.com/pappasam/nginx-language-server
Project-URL: Issues, https://github.com/pappasam/nginx-language-server/issues
Project-URL: Repository, https://github.com/pappasam/nginx-language-server
